scrape/__init__.py
scrape/main.py
scrape/scrape.py
tests/__init__.py
tests/test_scrape.py
scrape_easy-1.0.0.dist-info/METADATA
scrape_easy-1.0.0.dist-info/WHEEL
scrape_easy-1.0.0.dist-info/top_level.txt
scrape_easy-1.0.0.dist-info/RECORD
