Metadata-Version: 2.1
Name: scrape-easy
Version: 1.0.0
Summary: Automate scraping data with single functions call
Home-page: https://github.com/king-tomi/easy-scrape
Author: Ayodabo Tomisin
Author-email: ayodabooluwatomisin@gmail.com
License: MIT
Platform: UNKNOWN
Classifier: License :: OSI Approved :: MIT License
Classifier: Programming Language :: Python :: 3
Classifier: Programming Language :: Python :: 3.7
Requires-Dist: bs4
Requires-Dist: requests
Requires-Dist: pytest
